python_svdata-0.1.0.dist-info/METADATA
python_svdata-0.1.0.dist-info/WHEEL
python_svdata-0.1.0.dist-info/license_files/LICENSE
python_svdata/__init__.py
python_svdata/__init__.pyi
python_svdata/py.typed
python_svdata/python_svdata.pypy37-pp73-x86_64-linux-gnu.so
python_svdata-0.1.0.dist-info/RECORD
